requirements.txt
setup.py
django_daemon_command/__init__.py
django_daemon_command/models.py
django_daemon_command.egg-info/PKG-INFO
django_daemon_command.egg-info/SOURCES.txt
django_daemon_command.egg-info/dependency_links.txt
django_daemon_command.egg-info/requires.txt
django_daemon_command.egg-info/top_level.txt
django_daemon_command/management/__init__.py
django_daemon_command/management/base.py
django_daemon_command/migrations/0001_initial.py
django_daemon_command/migrations/__init__.py