Metadata-Version: 2.1
Name: django-daemon-command
Version: 2020.7.1
Summary: django DaemonCommand
Home-page: https://github.com/andrewp-as-is/django-daemon-command.py
License: Unlicense
Keywords: django daemon command
Platform: UNKNOWN
Classifier: Framework :: Django
Classifier: License :: Public Domain
Classifier: Operating System :: OS Independent
Classifier: Programming Language :: Python :: 3
